[
  {
    "homeTeam": "Dinamo Zagreb hr",
    "awayTeam": "es Celta Vigo",
    "score": "0-3"
  },
  {
    "homeTeam": "Nice fr",
    "awayTeam": "de Freiburg",
    "score": "1-3"
  },
  {
    "homeTeam": "Red Star rs",
    "awayTeam": "fr Lille",
    "score": "1-0"
  },
  {
    "homeTeam": "Basel ch",
    "awayTeam": "ro FCSB",
    "score": "3-1"
  },
  {
    "homeTeam": "Midtjylland dk",
    "awayTeam": "sct Celtic",
    "score": "3-1"
  },
  {
    "homeTeam": "Malmö se",
    "awayTeam": "gr Panathinaikos",
    "score": "0-1"
  },
  {
    "homeTeam": "Utrecht nl",
    "awayTeam": "pt Porto",
    "score": "1-1"
  },
  {
    "homeTeam": "Sturm Graz at",
    "awayTeam": "eng Nott'ham Forest",
    "score": "0-0"
  },
  {
    "homeTeam": "RB Salzburg at",
    "awayTeam": "nl Go Ahead Eag",
    "score": "2-0"
  },
  {
    "homeTeam": "Rangers sct",
    "awayTeam": "it Roma",
    "score": "0-2"
  },
  {
    "homeTeam": "Aston Villa eng",
    "awayTeam": "il Maccabi Tel Aviv",
    "score": "2-0"
  },
  {
    "homeTeam": "Braga pt",
    "awayTeam": "be Genk",
    "score": "3-4"
  },
  {
    "homeTeam": "Betis es",
    "awayTeam": "fr Lyon",
    "score": "2-0"
  },
  {
    "homeTeam": "Stuttgart de",
    "awayTeam": "nl Feyenoord",
    "score": "2-0"
  },
  {
    "homeTeam": "Ferencváros hu",
    "awayTeam": "bg Ludogorets",
    "score": "3-1"
  },
  {
    "homeTeam": "Bologna it",
    "awayTeam": "no Brann",
    "score": "0-0"
  },
  {
    "homeTeam": "Viktoria Plzeň cz",
    "awayTeam": "tr Fenerbahçe",
    "score": "0-0"
  },
  {
    "homeTeam": "PAOK gr",
    "awayTeam": "ch Young Boys",
    "score": "4-0"
  },
  {
    "homeTeam": "Sparta Prague cz",
    "awayTeam": "pl Raków",
    "score": "0-0"
  },
  {
    "homeTeam": "Mainz 05 de",
    "awayTeam": "it Fiorentina",
    "score": "2-1"
  },
  {
    "homeTeam": "NK Celje si",
    "awayTeam": "pl Legia Warsaw",
    "score": "2-1"
  },
  {
    "homeTeam": "AEK Athens gr",
    "awayTeam": "ie Shamrock Rovers",
    "score": "1-1"
  },
  {
    "homeTeam": "Shakhtar ua",
    "awayTeam": "is Breiðablik",
    "score": "2-0"
  },
  {
    "homeTeam": "KuPS fi",
    "awayTeam": "sk Slovan Bratislava",
    "score": "3-1"
  },
  {
    "homeTeam": "AÉK Lárnaka cy",
    "awayTeam": "sct Aberdeen",
    "score": "0-0"
  },
  {
    "homeTeam": "Crystal Palace eng",
    "awayTeam": "nl AZ Alkmaar",
    "score": "3-1"
  },
  {
    "homeTeam": "Shelbourne FC ie",
    "awayTeam": "xk KF Drita",
    "score": "0-1"
  },
  {
    "homeTeam": "Samsunspor tr",
    "awayTeam": "mt Ħamrun Spartans FC",
    "score": "3-0"
  },
  {
    "homeTeam": "Red Imps gi",
    "awayTeam": "hr Rijeka",
    "score": "1-1"
  },
  {
    "homeTeam": "Häcken se",
    "awayTeam": "fr Strasbourg",
    "score": "1-2"
  },
  {
    "homeTeam": "Rapid Wien at",
    "awayTeam": "ro CS U Craiova",
    "score": "0-1"
  },
  {
    "homeTeam": "Rayo Vallecano es",
    "awayTeam": "pl Lech Poznań",
    "score": "3-2"
  },
  {
    "homeTeam": "Shkëndija 79 mk",
    "awayTeam": "pl Jagiellonia",
    "score": "1-1"
  },
  {
    "homeTeam": "Lausanne-Sport ch",
    "awayTeam": "cy AC Omonia",
    "score": "1-1"
  },
  {
    "homeTeam": "FC Noah am",
    "awayTeam": "cz Sigma Olomouc",
    "score": "1-2"
  },
  {
    "homeTeam": "Dynamo Kyiv ua",
    "awayTeam": "ba Zrinjski Mostar",
    "score": "6-0"
  },
  {
    "homeTeam": "Reading",
    "awayTeam": "Stevenage",
    "score": "1-0"
  },
  {
    "homeTeam": "Hoffenheim",
    "awayTeam": "Freiburg",
    "score": "2-1"
  },
  {
    "homeTeam": "RB Leipzig",
    "awayTeam": "Carl-Zeiss Jena",
    "score": "2-0"
  },
  {
    "homeTeam": "Malavan",
    "awayTeam": "Shams Azar",
    "score": "0-0"
  },
  {
    "homeTeam": "Gol Gohar",
    "awayTeam": "Zob Ahan",
    "score": "1-2"
  },
  {
    "homeTeam": "Al-Hazem",
    "awayTeam": "Al-Khaleej",
    "score": "1-4"
  },
  {
    "homeTeam": "Al-Qadsiah",
    "awayTeam": "Al Kholood Saudi Club",
    "score": "4-0"
  },
  {
    "homeTeam": "Al-Riyadh SC",
    "awayTeam": "Damac",
    "score": "1-1"
  }
]